package/__init__.py
package/main.py
PyFuncExtras-0.0.1.dist-info/LICENSE
PyFuncExtras-0.0.1.dist-info/METADATA
PyFuncExtras-0.0.1.dist-info/WHEEL
PyFuncExtras-0.0.1.dist-info/top_level.txt
PyFuncExtras-0.0.1.dist-info/RECORD
