Metadata-Version: 2.1
Name: PyFuncExtras
Version: 0.0.1
Summary: extra python functions
Home-page: https://github.com/EnderBender08/pyfextras
Author: EnderBender
Author-email: arjunrules55@gmail.com
License: UNKNOWN
Project-URL: Bug Tracker, https://github.com/EnderBender08/pyfextras/issues
Platform: UNKNOWN
Classifier: Programming Language :: Python :: 3
Classifier: License :: OSI Approved :: MIT License
Classifier: Operating System :: OS Independent
Requires-Python: >=3.8
License-File: LICENSE
